jax_cuda11_plugin/_blas.so
jax_cuda11_plugin/_linalg.so
jax_cuda11_plugin/_prng.so
jax_cuda11_plugin/_rnn.so
jax_cuda11_plugin/_solver.so
jax_cuda11_plugin/_sparse.so
jax_cuda11_plugin/_triton.so
jax_cuda11_plugin/_versions.so
jax_cuda11_plugin/cuda_plugin_extension.so
jax_cuda11_plugin/version.py
jax_cuda11_plugin/nvvm/libdevice/libdevice.10.bc
jax_cuda11_plugin-0.4.25.dist-info/METADATA
jax_cuda11_plugin-0.4.25.dist-info/WHEEL
jax_cuda11_plugin-0.4.25.dist-info/top_level.txt
jax_cuda11_plugin-0.4.25.dist-info/RECORD
