Metadata-Version: 2.1
Name: jax-cuda11-plugin
Version: 0.4.25
Summary: JAX Plugin for NVIDIA GPUs
Home-page: https://github.com/google/jax
Author: JAX team
Author-email: jax-dev@google.com
License: Apache-2.0
Classifier: Development Status :: 3 - Alpha
Classifier: Programming Language :: Python :: 3.9
Classifier: Programming Language :: Python :: 3.10
Classifier: Programming Language :: Python :: 3.11
Classifier: Programming Language :: Python :: 3.12
Requires-Python: >=3.9
Requires-Dist: jax-cuda11-pjrt ==0.4.25
